[
  {"nombre_materia":"Fundamentos de programación","numero_creditos":3,"descripcion":"Principios básicos de programación: algoritmos, estructuras de control y resolución de problemas."},
  {"nombre_materia":"Introducción a la ingeniería","numero_creditos":2,"descripcion":"Panorama general de la ingeniería como disciplina y sus aplicaciones profesionales."},
  {"nombre_materia":"Sociedad y tecnología","numero_creditos":2,"descripcion":"Análisis de la relación entre tecnología, sociedad y desarrollo sustentable."},
  {"nombre_materia":"Laboratorio de programación II","numero_creditos":2,"descripcion":"Prácticas de laboratorio para afianzar técnicas de programación y uso de herramientas."},
  {"nombre_materia":"Programación","numero_creditos":3,"descripcion":"Profundización en paradigmas de programación, estructuras de datos y buenas prácticas."},
  {"nombre_materia":"Estructura de datos","numero_creditos":3,"descripcion":"Estudio de estructuras de datos fundamentales: listas, pilas, colas, árboles y grafos."},
  {"nombre_materia":"Base de datos I","numero_creditos":3,"descripcion":"Modelado de datos, diseño de bases de datos relacionales y consultas SQL básicas."},
  {"nombre_materia":"Electiva disciplinar I","numero_creditos":2,"descripcion":"Electiva temática para profundizar en un área concreta de la disciplina."},
  {"nombre_materia":"Programación orientada a objetivos","numero_creditos":3,"descripcion":"Paradigma de programación orientada a objetos y diseño de software modular."},
  {"nombre_materia":"Electrónica análoga","numero_creditos":3,"descripcion":"Fundamentos de circuitos analógicos, componentes y comportamiento en señales continuas."},
  {"nombre_materia":"Electiva disciplinar II","numero_creditos":2,"descripcion":"Asignatura optativa para especialización técnica dentro del plan de estudios."},
  {"nombre_materia":"Electiva disciplinar (base de datos)","numero_creditos":2,"descripcion":"Optativa específica para profundizar en tecnologías y administración de bases de datos."},
  {"nombre_materia":"Métodos numéricos","numero_creditos":3,"descripcion":"Algoritmos numéricos para la resolución aproximada de problemas matemáticos y de ingeniería."},
  {"nombre_materia":"Sistemas operativos","numero_creditos":3,"descripcion":"Conceptos de sistemas operativos: procesos, concurrencia, gestión de memoria y archivos."},
  {"nombre_materia":"Teoría general de sistemas","numero_creditos":2,"descripcion":"Principios de teoría de sistemas y su aplicación al análisis de sistemas complejos."},
  {"nombre_materia":"Arquitectura del computador","numero_creditos":3,"descripcion":"Estructura y organización de computadores: CPU, memoria y comunicación entre componentes."},
  {"nombre_materia":"Electrónica digital","numero_creditos":3,"descripcion":"Circuitos digitales, lógica combinacional y secuencial aplicados a sistemas digitales."},
  {"nombre_materia":"Gestión financiera","numero_creditos":2,"descripcion":"Conceptos financieros básicos para la toma de decisiones en proyectos tecnológicos."},
  {"nombre_materia":"Investigación de operaciones","numero_creditos":3,"descripcion":"Modelos de optimización, programación lineal y técnicas de apoyo a la toma de decisiones."},
  {"nombre_materia":"Ingeniería de software","numero_creditos":3,"descripcion":"Metodologías de desarrollo de software, ciclo de vida, pruebas y aseguramiento de calidad."},
  {"nombre_materia":"Redes computacionales I","numero_creditos":3,"descripcion":"Fundamentos de redes: modelos OSI/TCP, protocolos y arquitectura de redes."},
  {"nombre_materia":"Auditoría informática","numero_creditos":2,"descripcion":"Control, evaluación y auditoría de sistemas de información y seguridad informática."},
  {"nombre_materia":"Electiva disciplinar (redes)","numero_creditos":2,"descripcion":"Asignatura optativa centrada en tecnologías y protocolos de redes avanzadas."},
  {"nombre_materia":"Ingeniería de software II","numero_creditos":3,"descripcion":"Profundización en diseño de arquitecturas, patrones, pruebas y mantenimiento de software."},
  {"nombre_materia":"Legislación de software","numero_creditos":2,"descripcion":"Normativa, propiedad intelectual y aspectos legales relacionados con el desarrollo de software."},
  {"nombre_materia":"Sistemas de control","numero_creditos":3,"descripcion":"Teoría y diseño de sistemas de control y su implementación en procesos automatizados."},
  {"nombre_materia":"Administración de sistemas de información","numero_creditos":3,"descripcion":"Gestión de infraestructuras de TI, políticas, continuidad del negocio y servicios."},
  {"nombre_materia":"Compiladores","numero_creditos":3,"descripcion":"Principios del diseño de compiladores: análisis léxico, sintáctico y generación de código."},
  {"nombre_materia":"Electiva disciplinar III","numero_creditos":2,"descripcion":"Optativa técnica para profundizar en áreas especializadas de la carrera."},
  {"nombre_materia":"Inteligencia artificial","numero_creditos":3,"descripcion":"Introducción a técnicas de IA: aprendizaje automático, búsqueda y representación de conocimiento."},
  {"nombre_materia":"Sistemas distribuidos","numero_creditos":3,"descripcion":"Modelos y técnicas para el diseño e implementación de sistemas distribuidos y paralelos."},
  {"nombre_materia":"Formulación de proyectos tecnológicos","numero_creditos":3,"descripcion":"Metodologías para proponer, justificar y estructurar proyectos tecnológicos e innovación."},
  {"nombre_materia":"Proyecto","numero_creditos":3,"descripcion":"Desarrollo inicial de un proyecto de grado o trabajo de investigación aplicado."},
  {"nombre_materia":"Simulación digital","numero_creditos":3,"descripcion":"Modelado y simulación por computadora de procesos y sistemas para análisis y optimización."},
  {"nombre_materia":"Proyecto II","numero_creditos":3,"descripcion":"Culminación y defensa del proyecto de grado con resultados aplicados y evaluación académica."}
]
